pyprojectlib/LICENSE.template
pyprojectlib/README.template
pyprojectlib/__init__.py
pyprojectlib/cli.py
pyprojectlib/constants.py
pyprojectlib/helper.py
pyprojectlib/py.typed
pyprojectlib/pypackage.py
pyprojectlib/pyproject.py
pyprojectlib/pyrepo.py
pyprojectlib/pyuser.py
pyprojectlib-0.0.8.dist-info/licenses/LICENSE.txt
pyprojectlib-0.0.8.dist-info/METADATA
pyprojectlib-0.0.8.dist-info/WHEEL
pyprojectlib-0.0.8.dist-info/entry_points.txt
pyprojectlib-0.0.8.dist-info/top_level.txt
pyprojectlib-0.0.8.dist-info/RECORD
