Metadata-Version: 2.4
Name: pyprojectlib
Version: 0.0.8
Author-email: Jason Krist <jkrist2696@gmail.com>
License-Expression: GPL-3.0-or-later
Project-URL: Homepage, https://github.com/jkrist2696/pyprojectlib
Classifier: Programming Language :: Python :: 3
Classifier: Operating System :: Microsoft :: Windows
Classifier: Operating System :: Unix
Requires-Python: >=3.6
License-File: LICENSE.txt
Requires-Dist: pipreqs>=0.4.13
Requires-Dist: cleandoc>=0.0.13
Requires-Dist: GitPython>=3.1.40
Requires-Dist: pytest>=7.4.3
Requires-Dist: build
Requires-Dist: twine
Requires-Dist: tomli
Requires-Dist: tomli-w
Requires-Dist: types-requests
Requires-Dist: types-setuptools
Requires-Dist: selenium
Dynamic: license-file
